XBStrapDistro/__init__.py
XBStrapSQLite/__init__.py
xbdistro_tools-0.2.1.dist-info/LICENSE
xbdistro_tools-0.2.1.dist-info/METADATA
xbdistro_tools-0.2.1.dist-info/WHEEL
xbdistro_tools-0.2.1.dist-info/top_level.txt
xbdistro_tools-0.2.1.dist-info/RECORD
